{
	"animations": [
		{
			"offsets": [
				0,
				0
			],
			"indices": [],
			"fps": 24,
			"anim": "idle",
			"loop": false,
			"name": "angry rosanna idle"
		},
		{
			"offsets": [
				15,
				27
			],
			"indices": [],
			"fps": 24,
			"anim": "singLEFT",
			"loop": false,
			"name": "angry rosanna left"
		},
		{
			"offsets": [
				-29,
				-126
			],
			"indices": [],
			"fps": 24,
			"anim": "singDOWN",
			"loop": false,
			"name": "angry rosanna down"
		},
		{
			"offsets": [
				97,
				127
			],
			"indices": [],
			"fps": 24,
			"anim": "singUP",
			"loop": false,
			"name": "angry rosanna up"
		},
		{
			"offsets": [
				-93,
				-123
			],
			"indices": [],
			"fps": 24,
			"anim": "singRIGHT",
			"loop": false,
			"name": "angry rosanna right"
		},
		{
			"offsets": [
				1295,
				87
			],
			"indices": [],
			"fps": 24,
			"anim": "fuck this",
			"loop": false,
			"name": "rosanna lost it"
		}
	],
	"no_antialiasing": false,
	"image": "characters/rosie_assets 2",
	"position": [
		0,
		0
	],
	"healthicon": "rosie",
	"flip_x": false,
	"healthbar_colors": [
		255,
		136,
		215
	],
	"camera_position": [
		0,
		0
	],
	"sing_duration": 6.1,
	"scale": 1
}