{"name":null,"assets":"aoy4:pathy53:assets%2FbonusWeek%2Fimages%2FBallisticBackground.pngy4:sizei7631536y4:typey5:IMAGEy2:idR1goR0y53:assets%2FbonusWeek%2Fimages%2FBallisticBackground.xmlR2i2467R3y4:TEXTR5R6goR0y48:assets%2FbonusWeek%2Fimages%2Fthefunnyeffect.pngR2i487155R3R4R5R8goR0y44:assets%2FbonusWeek%2Fimages%2FwhittyBack.pngR2i359480R3R4R5R9goR0y44:assets%2FbonusWeek%2Fimages%2FwhittyBack.xcfR2i488243R3y6:BINARYR5R10goR0y45:assets%2FbonusWeek%2Fimages%2FwhittyFront.pngR2i42519R3R4R5R12gh","rootPath":"../","version":2,"libraryArgs":[],"libraryType":null}